LICENSE
README.md
setup.py
src/agentkit/__init__.py
src/agentkit/after_query.py
src/agentkit/base_node.py
src/agentkit/compose_prompt.py
src/agentkit/exceptions.py
src/agentkit/graph.py
src/agentkit/node.py
src/agentkit/node_functions.py
src/agentkit/utils.py
src/agentkit/llm_api/GPT.py
src/agentkit/llm_api/__init__.py
src/agentkit/llm_api/base.py
src/agentkit/llm_api/claude.py
src/agentkit/llm_api/ollama.py
src/agentkit/llm_api/utils.py
src/agentkit_llm.egg-info/PKG-INFO
src/agentkit_llm.egg-info/SOURCES.txt
src/agentkit_llm.egg-info/dependency_links.txt
src/agentkit_llm.egg-info/entry_points.txt
src/agentkit_llm.egg-info/requires.txt
src/agentkit_llm.egg-info/top_level.txt