Metadata-Version: 2.1
Name: agentkit-llm
Version: 0.1.8.post1
Summary: A LLM prompting framework for LLM agents
Home-page: https://github.com/rhyswynn/AgentKit
Author: AgentKit Team
License: CC-BY-4.0-Attribution
Classifier: Intended Audience :: Science/Research
Classifier: Programming Language :: Python :: 3
Classifier: Topic :: Scientific/Engineering :: Artificial Intelligence
License-File: LICENSE
Requires-Dist: colorama
Requires-Dist: numpy
Requires-Dist: ruamel.yaml
Provides-Extra: logging
Requires-Dist: wandb; extra == "logging"
Provides-Extra: proprietary
Requires-Dist: wandb; extra == "proprietary"
Requires-Dist: openai; extra == "proprietary"
Requires-Dist: anthropic; extra == "proprietary"
Requires-Dist: tiktoken; extra == "proprietary"
Provides-Extra: all
Requires-Dist: wandb; extra == "all"
Requires-Dist: openai; extra == "all"
Requires-Dist: anthropic; extra == "all"
Requires-Dist: tiktoken; extra == "all"
Requires-Dist: llama; extra == "all"
